google/cloud/documentai_toolbox/__init__.py
google/cloud/documentai_toolbox/constants.py
google/cloud/documentai_toolbox/py.typed
google/cloud/documentai_toolbox/version.py
google/cloud/documentai_toolbox/converters/__init__.py
google/cloud/documentai_toolbox/converters/converter.py
google/cloud/documentai_toolbox/converters/vision_helpers.py
google/cloud/documentai_toolbox/converters/config/__init__.py
google/cloud/documentai_toolbox/converters/config/bbox_conversion.py
google/cloud/documentai_toolbox/converters/config/block.py
google/cloud/documentai_toolbox/templates/hocr_document_template.xml.j2
google/cloud/documentai_toolbox/utilities/__init__.py
google/cloud/documentai_toolbox/utilities/docai_utilities.py
google/cloud/documentai_toolbox/utilities/gcs_utilities.py
google/cloud/documentai_toolbox/wrappers/__init__.py
google/cloud/documentai_toolbox/wrappers/document.py
google/cloud/documentai_toolbox/wrappers/entity.py
google/cloud/documentai_toolbox/wrappers/page.py
google_cloud_documentai_toolbox-0.15.0a0.dist-info/LICENSE
google_cloud_documentai_toolbox-0.15.0a0.dist-info/METADATA
google_cloud_documentai_toolbox-0.15.0a0.dist-info/WHEEL
google_cloud_documentai_toolbox-0.15.0a0.dist-info/top_level.txt
google_cloud_documentai_toolbox-0.15.0a0.dist-info/RECORD
